<?xml version="1.0" encoding="utf-8" ?>
<dwsync>
<file name="Dsc01053.jpg" server="ftp.minkattklubb.se" local="129511692000000000" remote="131902893600000000" Dst="1" />
<file name="Dsc01054.jpg" server="ftp.minkattklubb.se" local="129511692000000000" remote="131902893600000000" Dst="1" />
<file name="Dsc01055.jpg" server="ftp.minkattklubb.se" local="129511692000000000" remote="131902893600000000" Dst="1" />
<file name="Dsc01056.jpg" server="ftp.minkattklubb.se" local="129511692000000000" remote="131902893600000000" Dst="1" />
<file name="Dsc01058.jpg" server="ftp.minkattklubb.se" local="129511692000000000" remote="131902893600000000" Dst="1" />
<file name="Dsc01059.jpg" server="ftp.minkattklubb.se" local="129511692000000000" remote="131902893600000000" Dst="1" />
<file name="Dsc01060.jpg" server="ftp.minkattklubb.se" local="129511692000000000" remote="131902893600000000" Dst="1" />
<file name="Dsc01063.jpg" server="ftp.minkattklubb.se" local="129511692000000000" remote="131902893600000000" Dst="1" />
<file name="Dsc01064.jpg" server="ftp.minkattklubb.se" local="129511692000000000" remote="131902893600000000" Dst="1" />
<file name="Dsc01066.jpg" server="ftp.minkattklubb.se" local="129511692000000000" remote="131902893600000000" Dst="1" />
<file name="Dsc01067.jpg" server="ftp.minkattklubb.se" local="129511692000000000" remote="131902893600000000" Dst="1" />
<file name="Dsc01069.jpg" server="ftp.minkattklubb.se" local="129511692000000000" remote="131902893600000000" Dst="1" />
<file name="Dsc01070.jpg" server="ftp.minkattklubb.se" local="129511692000000000" remote="131902893600000000" Dst="1" />
<file name="Dsc01072.jpg" server="ftp.minkattklubb.se" local="129511692000000000" remote="131902893600000000" Dst="1" />
<file name="Dsc01074.jpg" server="ftp.minkattklubb.se" local="129511692000000000" remote="131902893600000000" Dst="1" />
<file name="Dsc01075.jpg" server="ftp.minkattklubb.se" local="129511692000000000" remote="131902893600000000" Dst="1" />
<file name="Dsc01076.jpg" server="ftp.minkattklubb.se" local="129511692000000000" remote="131902893600000000" Dst="1" />
<file name="Dsc01077.jpg" server="ftp.minkattklubb.se" local="129511692000000000" remote="131902893600000000" Dst="1" />
<file name="Dsc01078.jpg" server="ftp.minkattklubb.se" local="129511692000000000" remote="131902893600000000" Dst="1" />
<file name="Dsc01079.jpg" server="ftp.minkattklubb.se" local="129511692000000000" remote="131902893600000000" Dst="1" />
<file name="Dsc01080.jpg" server="ftp.minkattklubb.se" local="129511692000000000" remote="131902893600000000" Dst="1" />
<file name="Dsc01081.jpg" server="ftp.minkattklubb.se" local="129511692000000000" remote="131902893600000000" Dst="1" />
<file name="Dsc01082.jpg" server="ftp.minkattklubb.se" local="129511692000000000" remote="131902893600000000" Dst="1" />
<file name="Dsc01083.jpg" server="ftp.minkattklubb.se" local="129511692000000000" remote="131902893600000000" Dst="1" />
<file name="Dsc01084.jpg" server="ftp.minkattklubb.se" local="129511692000000000" remote="131902893600000000" Dst="1" />
<file name="Dsc01085.jpg" server="ftp.minkattklubb.se" local="129511692000000000" remote="131902893600000000" Dst="1" />
<file name="Dsc01086.jpg" server="ftp.minkattklubb.se" local="129511692000000000" remote="131902893600000000" Dst="1" />
<file name="Dsc01087.jpg" server="ftp.minkattklubb.se" local="129511692000000000" remote="131902893600000000" Dst="1" />
<file name="Dsc01088.jpg" server="ftp.minkattklubb.se" local="129511692000000000" remote="131902893600000000" Dst="1" />
<file name="Dsc01089.jpg" server="ftp.minkattklubb.se" local="129511692000000000" remote="131902893600000000" Dst="1" />
<file name="Dsc01092.jpg" server="ftp.minkattklubb.se" local="129511692000000000" remote="131902893600000000" Dst="1" />
<file name="Dsc01093.jpg" server="ftp.minkattklubb.se" local="129511692000000000" remote="131902893600000000" Dst="1" />
<file name="Dsc01094.jpg" server="ftp.minkattklubb.se" local="129511692000000000" remote="131902893600000000" Dst="1" />
<file name="Dsc01095.jpg" server="ftp.minkattklubb.se" local="129511692000000000" remote="131902893600000000" Dst="1" />
<file name="Dsc01097.jpg" server="ftp.minkattklubb.se" local="129511692000000000" remote="131902893600000000" Dst="1" />
<file name="Dsc01096.jpg" server="ftp.minkattklubb.se" local="129511692000000000" remote="131902893600000000" Dst="1" />
<file name="Dsc01099.jpg" server="ftp.minkattklubb.se" local="129511692000000000" remote="131902893600000000" Dst="1" />
<file name="Dsc01101.jpg" server="ftp.minkattklubb.se" local="129511692000000000" remote="131902893600000000" Dst="1" />
<file name="Dsc01102.jpg" server="ftp.minkattklubb.se" local="129511692000000000" remote="131902893600000000" Dst="1" />
<file name="Dsc01100.jpg" server="ftp.minkattklubb.se" local="129511692000000000" remote="131902893600000000" Dst="1" />
<file name="Dsc01103.jpg" server="ftp.minkattklubb.se" local="129511692000000000" remote="131902893600000000" Dst="1" />
<file name="Dsc01105.jpg" server="ftp.minkattklubb.se" local="129511692000000000" remote="131902893600000000" Dst="1" />
<file name="Dsc01104.jpg" server="ftp.minkattklubb.se" local="129511692000000000" remote="131902893600000000" Dst="1" />
<file name="Dsc01107.jpg" server="ftp.minkattklubb.se" local="129511692000000000" remote="131902893600000000" Dst="1" />
<file name="Dsc01108.jpg" server="ftp.minkattklubb.se" local="129511692000000000" remote="131902893600000000" Dst="1" />
<file name="Dsc01109.jpg" server="ftp.minkattklubb.se" local="129511692000000000" remote="131902893600000000" Dst="1" />
<file name="Dsc01110.jpg" server="ftp.minkattklubb.se" local="129511692000000000" remote="131902893600000000" Dst="1" />
<file name="Dsc01111.jpg" server="ftp.minkattklubb.se" local="129511692000000000" remote="131902893600000000" Dst="1" />
<file name="Dsc01112.jpg" server="ftp.minkattklubb.se" local="129511692000000000" remote="131902893600000000" Dst="1" />
<file name="Dsc01113.jpg" server="ftp.minkattklubb.se" local="129511692000000000" remote="131902893600000000" Dst="1" />
<file name="Dsc01114.jpg" server="ftp.minkattklubb.se" local="129511692000000000" remote="131902893600000000" Dst="1" />
<file name="Dsc01115.jpg" server="ftp.minkattklubb.se" local="129511692000000000" remote="131902893600000000" Dst="1" />
<file name="Dsc01116.jpg" server="ftp.minkattklubb.se" local="129511692000000000" remote="131902893600000000" Dst="1" />
<file name="Dsc01117.jpg" server="ftp.minkattklubb.se" local="129511692000000000" remote="131902893600000000" Dst="1" />
<file name="Dsc01119.jpg" server="ftp.minkattklubb.se" local="129511692000000000" remote="131902893600000000" Dst="1" />
<file name="Dsc01120.jpg" server="ftp.minkattklubb.se" local="129511692000000000" remote="131902893600000000" Dst="1" />
<file name="Dsc01121.jpg" server="ftp.minkattklubb.se" local="129511692000000000" remote="131902893600000000" Dst="1" />
<file name="Dsc01122.jpg" server="ftp.minkattklubb.se" local="129511692000000000" remote="131902893600000000" Dst="1" />
<file name="Dsc01123.jpg" server="ftp.minkattklubb.se" local="129511692000000000" remote="131902893600000000" Dst="1" />
<file name="Dsc01124.jpg" server="ftp.minkattklubb.se" local="129511692000000000" remote="131902893600000000" Dst="1" />
<file name="Dsc01125.jpg" server="ftp.minkattklubb.se" local="129511692000000000" remote="131902893600000000" Dst="1" />
<file name="Dsc01126.jpg" server="ftp.minkattklubb.se" local="129511692000000000" remote="131902893600000000" Dst="1" />
<file name="Dsc01127.jpg" server="ftp.minkattklubb.se" local="129511692000000000" remote="131902893600000000" Dst="1" />
<file name="Dsc01129.jpg" server="ftp.minkattklubb.se" local="129511692000000000" remote="131902893600000000" Dst="1" />
<file name="Dsc01128.jpg" server="ftp.minkattklubb.se" local="129511692000000000" remote="131902893600000000" Dst="1" />
<file name="Dsc01130.jpg" server="ftp.minkattklubb.se" local="129511692000000000" remote="131902893600000000" Dst="1" />
<file name="Dsc01131.jpg" server="ftp.minkattklubb.se" local="129511692000000000" remote="131902893600000000" Dst="1" />
<file name="Dsc01132.jpg" server="ftp.minkattklubb.se" local="129511692000000000" remote="131902893600000000" Dst="1" />
<file name="Dsc01133.jpg" server="ftp.minkattklubb.se" local="129511692000000000" remote="131902893600000000" Dst="1" />
<file name="Dsc01136.jpg" server="ftp.minkattklubb.se" local="129511692000000000" remote="131902893600000000" Dst="1" />
<file name="Dsc01137.jpg" server="ftp.minkattklubb.se" local="129511692000000000" remote="131902893600000000" Dst="1" />
<file name="Dsc01138.jpg" server="ftp.minkattklubb.se" local="129511692000000000" remote="131902893600000000" Dst="1" />
<file name="Dsc01139.jpg" server="ftp.minkattklubb.se" local="129511692000000000" remote="131902893600000000" Dst="1" />
<file name="Dsc01140.jpg" server="ftp.minkattklubb.se" local="129511692000000000" remote="131902893600000000" Dst="1" />
<file name="Dsc01141.jpg" server="ftp.minkattklubb.se" local="129511692000000000" remote="131902893600000000" Dst="1" />
<file name="Dsc01142.jpg" server="ftp.minkattklubb.se" local="129511692000000000" remote="131902893600000000" Dst="1" />
<file name="Dsc01143.jpg" server="ftp.minkattklubb.se" local="129511692000000000" remote="131902893600000000" Dst="1" />
<file name="Dsc01145.jpg" server="ftp.minkattklubb.se" local="129511692000000000" remote="131902893600000000" Dst="1" />
<file name="Dsc01147.jpg" server="ftp.minkattklubb.se" local="129511692000000000" remote="131902893600000000" Dst="1" />
<file name="Dsc01148.jpg" server="ftp.minkattklubb.se" local="129511692000000000" remote="131902893600000000" Dst="1" />
<file name="Dsc01149.jpg" server="ftp.minkattklubb.se" local="129511692000000000" remote="131902893600000000" Dst="1" />
<file name="Dsc01152.jpg" server="ftp.minkattklubb.se" local="129511692000000000" remote="131902893600000000" Dst="1" />
<file name="Dsc01150.jpg" server="ftp.minkattklubb.se" local="129511692000000000" remote="131902893600000000" Dst="1" />
<file name="Dsc01153.jpg" server="ftp.minkattklubb.se" local="129511692000000000" remote="131902893600000000" Dst="1" />
<file name="Dsc01154.jpg" server="ftp.minkattklubb.se" local="129511692000000000" remote="131902893600000000" Dst="1" />
<file name="Dsc01157.jpg" server="ftp.minkattklubb.se" local="129511692000000000" remote="131902893600000000" Dst="1" />
<file name="Dsc01158.jpg" server="ftp.minkattklubb.se" local="129511692000000000" remote="131902893600000000" Dst="1" />
<file name="Dsc01159.jpg" server="ftp.minkattklubb.se" local="129511692000000000" remote="131902893600000000" Dst="1" />
<file name="Dsc01161.jpg" server="ftp.minkattklubb.se" local="129511692600000000" remote="131902893600000000" Dst="1" />
<file name="Dsc01163.jpg" server="ftp.minkattklubb.se" local="129511692600000000" remote="131902893600000000" Dst="1" />
<file name="Dsc01167.jpg" server="ftp.minkattklubb.se" local="129511692600000000" remote="131902893600000000" Dst="1" />
<file name="Dsc01168.jpg" server="ftp.minkattklubb.se" local="129511692600000000" remote="131902893600000000" Dst="1" />
<file name="Dsc01170.jpg" server="ftp.minkattklubb.se" local="129511692600000000" remote="131902893600000000" Dst="1" />
<file name="Dsc01172.jpg" server="ftp.minkattklubb.se" local="129511692600000000" remote="131902893600000000" Dst="1" />
<file name="Dsc01173.jpg" server="ftp.minkattklubb.se" local="129511692600000000" remote="131902893600000000" Dst="1" />
<file name="Dsc01176.jpg" server="ftp.minkattklubb.se" local="129511692600000000" remote="131902893600000000" Dst="1" />
<file name="Dsc01179.jpg" server="ftp.minkattklubb.se" local="129511692600000000" remote="131902893600000000" Dst="1" />
<file name="Dsc01180.jpg" server="ftp.minkattklubb.se" local="129511692600000000" remote="131902893600000000" Dst="1" />
<file name="Dsc01181.jpg" server="ftp.minkattklubb.se" local="129511692600000000" remote="131902893600000000" Dst="1" />
<file name="Dsc01184.jpg" server="ftp.minkattklubb.se" local="129511692600000000" remote="131902893600000000" Dst="1" />
<file name="Dsc01183.jpg" server="ftp.minkattklubb.se" local="129511692600000000" remote="131902893600000000" Dst="1" />
<file name="Dsc01185.jpg" server="ftp.minkattklubb.se" local="129511692600000000" remote="131902893600000000" Dst="1" />
<file name="Dsc01188.jpg" server="ftp.minkattklubb.se" local="129511692600000000" remote="131902893600000000" Dst="1" />
<file name="Dsc01187.jpg" server="ftp.minkattklubb.se" local="129511692600000000" remote="131902893600000000" Dst="1" />
<file name="Dsc01191.jpg" server="ftp.minkattklubb.se" local="129511692600000000" remote="131902893600000000" Dst="1" />
<file name="Dsc01192.jpg" server="ftp.minkattklubb.se" local="129511692600000000" remote="131902893600000000" Dst="1" />
<file name="Dsc01193.jpg" server="ftp.minkattklubb.se" local="129511692600000000" remote="131902893600000000" Dst="1" />
<file name="Dsc01195.jpg" server="ftp.minkattklubb.se" local="129511692600000000" remote="131902893600000000" Dst="1" />
<file name="Dsc01202.jpg" server="ftp.minkattklubb.se" local="129511692600000000" remote="131902893600000000" Dst="1" />
<file name="Dsc01204.jpg" server="ftp.minkattklubb.se" local="129511692600000000" remote="131902893600000000" Dst="1" />
<file name="Dsc01206.jpg" server="ftp.minkattklubb.se" local="129511692600000000" remote="131902893600000000" Dst="1" />
<file name="Dsc01209.jpg" server="ftp.minkattklubb.se" local="129511692600000000" remote="131902893600000000" Dst="1" />
<file name="Dsc01210.jpg" server="ftp.minkattklubb.se" local="129511692600000000" remote="131902893600000000" Dst="1" />
<file name="Dsc01212.jpg" server="ftp.minkattklubb.se" local="129511692600000000" remote="131902893600000000" Dst="1" />
<file name="Dsc01213.jpg" server="ftp.minkattklubb.se" local="129511692600000000" remote="131902893600000000" Dst="1" />
<file name="Dsc01214.jpg" server="ftp.minkattklubb.se" local="129511692600000000" remote="131902893600000000" Dst="1" />
<file name="Dsc01215.jpg" server="ftp.minkattklubb.se" local="129511692600000000" remote="131902893600000000" Dst="1" />
<file name="Dsc01216.jpg" server="ftp.minkattklubb.se" local="129511692600000000" remote="131902893600000000" Dst="1" />
<file name="Dsc01220.jpg" server="ftp.minkattklubb.se" local="129511692600000000" remote="131902893600000000" Dst="1" />
</dwsync>