<?xml version="1.0" encoding="utf-8" ?>
<dwsync>
<file name="245.jpg" server="ftp.minkattklubb.se" local="129040839000000000" remote="131902891200000000" Dst="1" />
<file name="246.jpg" server="ftp.minkattklubb.se" local="129040839000000000" remote="131902891200000000" Dst="1" />
<file name="249.jpg" server="ftp.minkattklubb.se" local="129040839000000000" remote="131902891200000000" Dst="1" />
<file name="253.jpg" server="ftp.minkattklubb.se" local="129040839000000000" remote="131902891200000000" Dst="1" />
<file name="260.jpg" server="ftp.minkattklubb.se" local="129040839000000000" remote="131902891200000000" Dst="1" />
<file name="264.jpg" server="ftp.minkattklubb.se" local="129040839000000000" remote="131902891200000000" Dst="1" />
<file name="285.jpg" server="ftp.minkattklubb.se" local="129040839000000000" remote="131902891200000000" Dst="1" />
<file name="289.jpg" server="ftp.minkattklubb.se" local="129040839000000000" remote="131902891200000000" Dst="1" />
</dwsync>